pyfixfmt/__init__.py
pyfixfmt/__main__.py
pyfixfmt-0.9.2.dist-info/LICENSE
pyfixfmt-0.9.2.dist-info/WHEEL
pyfixfmt-0.9.2.dist-info/METADATA
pyfixfmt-0.9.2.dist-info/RECORD
