Metadata-Version: 2.1
Name: pyfixfmt
Version: 0.9.2
Summary: Run several python fixers over a python file, to provide simple, deterministic code formatting.
Home-page: https://github.com/untitled-ai/pyfixfmt
License: MIT
Author: TJ DeVries
Author-email: devries.timothyj@gmail.com
Requires-Python: >=3.6,<4.0
Classifier: License :: OSI Approved :: MIT License
Classifier: Programming Language :: Python :: 3
Classifier: Programming Language :: Python :: 3.6
Classifier: Programming Language :: Python :: 3.7
Classifier: Programming Language :: Python :: 3.8
Classifier: Programming Language :: Python :: 3.9
Requires-Dist: autoflake (>=1.4)
Requires-Dist: black (>=20.8b1)
Requires-Dist: isort (>=4.3.21)
Project-URL: Repository, https://github.com/untitled-ai/pyfixfmt
